sync_with_uv/__init__.py
sync_with_uv/__main__.py
sync_with_uv/_version.py
sync_with_uv/cli.py
sync_with_uv/py.typed
sync_with_uv/repo_data.py
sync_with_uv/sync_with_uv.py
sync_with_uv-0.4.0.dist-info/METADATA
sync_with_uv-0.4.0.dist-info/WHEEL
sync_with_uv-0.4.0.dist-info/entry_points.txt
sync_with_uv-0.4.0.dist-info/RECORD
