Metadata-Version: 2.4
Name: sync-with-uv
Version: 0.4.0
Summary: Sync '.pre-commit-config.yaml' from 'uv.lock'.
Project-URL: source, https://github.com/tsvikas/sync-with-uv
Project-URL: changelog, https://github.com/tsvikas/sync-with-uv/blob/main/CHANGELOG.md
Project-URL: issues, https://github.com/tsvikas/sync-with-uv/issues
Author-email: Tsvika Shapira <tsvikas@gmail.com>
License-Expression: MIT
Keywords: automation,dependency-management,developer-tools,pre-commit,python-packaging,uv,version-sync
Classifier: Development Status :: 4 - Beta
Classifier: Intended Audience :: Developers
Classifier: Operating System :: OS Independent
Classifier: Programming Language :: Python
Classifier: Programming Language :: Python :: 3
Classifier: Programming Language :: Python :: 3 :: Only
Classifier: Programming Language :: Python :: 3.10
Classifier: Programming Language :: Python :: 3.11
Classifier: Programming Language :: Python :: 3.12
Classifier: Programming Language :: Python :: 3.13
Classifier: Topic :: Software Development
Classifier: Topic :: Software Development :: Quality Assurance
Classifier: Typing :: Typed
Requires-Python: >=3.10
Requires-Dist: click>=8.2.1
Requires-Dist: colorama>=0.4.6
Requires-Dist: tomli>=2
Requires-Dist: typer>=0.13
